binning_and_iv/__init__.py
binning_and_iv/prediction.py
aspire_iv-1.1.0.dist-info/METADATA
aspire_iv-1.1.0.dist-info/WHEEL
aspire_iv-1.1.0.dist-info/top_level.txt
aspire_iv-1.1.0.dist-info/RECORD
