Metadata-Version: 2.1
Name: aspire-iv
Version: 1.1.0
Summary: UNKNOWN
Home-page: UNKNOWN
Author: Girish Kumar R M
Author-email: 
License: UNKNOWN
Keywords: iv_and_prediction
Platform: UNKNOWN
Requires-Dist: scikit-learn
